numan_plus/__init__.py
numan_plus/compute_anova.py
numan_plus/compute_tunings.py
numan_plus/merge_segmented_planes.py
numan_plus/new_report.py
numan_plus-0.4.8.dist-info/METADATA
numan_plus-0.4.8.dist-info/WHEEL
numan_plus-0.4.8.dist-info/licenses/LICENSE
numan_plus-0.4.8.dist-info/RECORD
