Metadata-Version: 2.3
Name: numan_plus
Version: 0.4.8
Summary: A package for additional functionalities in numan (https://github.com/LemonJust/numan)
Project-URL: Homepage, https://github.com/MirkoZanon/numan_plus
Project-URL: Bug Tracker, https://github.com/MirkoZanon/numan_plus/issues
Author-email: Mirko Zanon <mirkozanon91@gmail.com>
License-File: LICENSE
Classifier: License :: OSI Approved :: MIT License
Classifier: Operating System :: OS Independent
Classifier: Programming Language :: Python :: 3
Requires-Python: >=3.7
